[{"hizb_number":18,"id":1194,"juz_number":9,"verse_key":"8:34","verse_number":34,"words":[{"chapter_number":0,"code_v1":"ﭑ","id":36468,"line_number":1,"position":1},{"chapter_number":0,"code_v1":"ﭒ","id":36469,"line_number":1,"position":2},{"chapter_number":0,"code_v1":"ﭓ","id":36470,"line_number":1,"position":3},{"chapter_number":0,"code_v1":"ﭔ","id":36471,"line_number":1,"position":4},{"chapter_number":0,"code_v1":"ﭕ","id":36472,"line_number":1,"position":5},{"chapter_number":0,"code_v1":"ﭖ","id":36473,"line_number":1,"position":6},{"chapter_number":0,"code_v1":"ﭗ","id":36474,"line_number":1,"position":7},{"chapter_number":0,"code_v1":"ﭘ","id":36475,"line_number":1,"position":8},{"chapter_number":0,"code_v1":"ﭙ","id":36476,"line_number":1,"position":9},{"chapter_number":0,"code_v1":"ﭚ","id":36477,"line_number":2,"position":10},{"chapter_number":0,"code_v1":"ﭛ","id":36478,"line_number":2,"position":11},{"chapter_number":0,"code_v1":"ﭜ","id":36479,"line_number":2,"position":12},{"chapter_number":0,"code_v1":"ﭝ","id":36480,"line_number":2,"position":13},{"chapter_number":0,"code_v1":"ﭞ","id":36481,"line_number":2,"position":14},{"chapter_number":0,"code_v1":"ﭟ","id":36482,"line_number":2,"position":15},{"chapter_number":0,"code_v1":"ﭠ","id":36483,"line_number":2,"position":16},{"chapter_number":0,"code_v1":"ﭡ","id":36484,"line_number":2,"position":17},{"chapter_number":0,"code_v1":"ﭢ","id":36485,"line_number":2,"position":18},{"chapter_number":0,"code_v1":"ﭣ","id":36486,"line_number":3,"position":19},{"chapter_number":0,"code_v1":"ﭤ","id":36487,"line_number":3,"position":20},{"chapter_number":0,"code_v1":"ﭥ","id":36488,"line_number":3,"position":21},{"chapter_number":0,"code_v1":"ﭦ","id":36489,"line_number":3,"position":22},{"chapter_number":0,"code_v1":"ﭧ","id":36490,"line_number":3,"position":23}]},{"hizb_number":18,"id":1195,"juz_number":9,"verse_key":"8:35","verse_number":35,"words":[{"chapter_number":0,"code_v1":"ﭨ","id":37177,"line_number":3,"position":1},{"chapter_number":0,"code_v1":"ﭩ","id":37178,"line_number":3,"position":2},{"chapter_number":0,"code_v1":"ﭪ","id":37179,"line_number":3,"position":3},{"chapter_number":0,"code_v1":"ﭫ","id":37180,"line_number":4,"position":4},{"chapter_number":0,"code_v1":"ﭬ","id":37181,"line_number":4,"position":5},{"chapter_number":0,"code_v1":"ﭭ","id":37182,"line_number":4,"position":6},{"chapter_number":0,"code_v1":"ﭮ","id":37183,"line_number":4,"position":7},{"chapter_number":0,"code_v1":"ﭯ","id":37184,"line_number":4,"position":8},{"chapter_number":0,"code_v1":"ﭰ","id":37185,"line_number":4,"position":9},{"chapter_number":0,"code_v1":"ﭱ","id":37186,"line_number":4,"position":10},{"chapter_number":0,"code_v1":"ﭲ","id":37187,"line_number":4,"position":11},{"chapter_number":0,"code_v1":"ﭳ","id":37188,"line_number":5,"position":12},{"chapter_number":0,"code_v1":"ﭴ","id":37189,"line_number":5,"position":13},{"chapter_number":0,"code_v1":"ﭵ","id":37190,"line_number":5,"position":14},{"chapter_number":0,"code_v1":"ﭶ","id":37191,"line_number":5,"position":15}]},{"hizb_number":18,"id":1196,"juz_number":9,"verse_key":"8:36","verse_number":36,"words":[{"chapter_number":0,"code_v1":"ﭷ","id":37978,"line_number":5,"position":1},{"chapter_number":0,"code_v1":"ﭸ","id":37979,"line_number":5,"position":2},{"chapter_number":0,"code_v1":"ﭹ","id":37980,"line_number":5,"position":3},{"chapter_number":0,"code_v1":"ﭺ","id":37981,"line_number":5,"position":4},{"chapter_number":0,"code_v1":"ﭻ","id":37982,"line_number":6,"position":5},{"chapter_number":0,"code_v1":"ﭼ","id":37983,"line_number":6,"position":6},{"chapter_number":0,"code_v1":"ﭽ","id":37984,"line_number":6,"position":7},{"chapter_number":0,"code_v1":"ﭾ","id":37985,"line_number":6,"position":8},{"chapter_number":0,"code_v1":"ﭿ","id":37986,"line_number":6,"position":9},{"chapter_number":0,"code_v1":"ﮀ","id":37987,"line_number":6,"position":10},{"chapter_number":0,"code_v1":"ﮁ","id":37988,"line_number":6,"position":11},{"chapter_number":0,"code_v1":"ﮂ","id":37989,"line_number":6,"position":12},{"chapter_number":0,"code_v1":"ﮃ","id":37990,"line_number":6,"position":13},{"chapter_number":0,"code_v1":"ﮄ","id":37991,"line_number":7,"position":14},{"chapter_number":0,"code_v1":"ﮅ","id":37992,"line_number":7,"position":15},{"chapter_number":0,"code_v1":"ﮆ","id":37993,"line_number":7,"position":16},{"chapter_number":0,"code_v1":"ﮇ","id":37994,"line_number":7,"position":17},{"chapter_number":0,"code_v1":"ﮈ","id":37995,"line_number":7,"position":18},{"chapter_number":0,"code_v1":"ﮉ","id":37996,"line_number":7,"position":19},{"chapter_number":0,"code_v1":"ﮊ","id":37997,"line_number":7,"position":20},{"chapter_number":0,"code_v1":"ﮋ","id":37998,"line_number":7,"position":21},{"chapter_number":0,"code_v1":"ﮌ","id":37999,"line_number":7,"position":22},{"chapter_number":0,"code_v1":"ﮍ","id":38000,"line_number":8,"position":23},{"chapter_number":0,"code_v1":"ﮎ","id":38001,"line_number":8,"position":24}]},{"hizb_number":18,"id":1197,"juz_number":9,"verse_key":"8:37","verse_number":37,"words":[{"chapter_number":0,"code_v1":"ﮏ","id":38815,"line_number":8,"position":1},{"chapter_number":0,"code_v1":"ﮐ","id":38816,"line_number":8,"position":2},{"chapter_number":0,"code_v1":"ﮑ","id":38817,"line_number":8,"position":3},{"chapter_number":0,"code_v1":"ﮒ","id":38818,"line_number":8,"position":4},{"chapter_number":0,"code_v1":"ﮓ","id":38819,"line_number":8,"position":5},{"chapter_number":0,"code_v1":"ﮔ","id":38820,"line_number":8,"position":6},{"chapter_number":0,"code_v1":"ﮕ","id":38821,"line_number":9,"position":7},{"chapter_number":0,"code_v1":"ﮖ","id":38822,"line_number":9,"position":8},{"chapter_number":0,"code_v1":"ﮗ","id":38823,"line_number":9,"position":9},{"chapter_number":0,"code_v1":"ﮘ","id":38824,"line_number":9,"position":10},{"chapter_number":0,"code_v1":"ﮙ","id":38825,"line_number":9,"position":11},{"chapter_number":0,"code_v1":"ﮚ","id":38826,"line_number":9,"position":12},{"chapter_number":0,"code_v1":"ﮛ","id":38827,"line_number":9,"position":13},{"chapter_number":0,"code_v1":"ﮜ","id":38828,"line_number":10,"position":14},{"chapter_number":0,"code_v1":"ﮝ","id":38829,"line_number":10,"position":15},{"chapter_number":0,"code_v1":"ﮞ","id":38830,"line_number":10,"position":16},{"chapter_number":0,"code_v1":"ﮟ","id":38831,"line_number":10,"position":17},{"chapter_number":0,"code_v1":"ﮠ","id":38832,"line_number":10,"position":18},{"chapter_number":0,"code_v1":"ﮡ","id":38833,"line_number":10,"position":19},{"chapter_number":0,"code_v1":"ﮢ","id":38834,"line_number":10,"position":20}]},{"hizb_number":18,"id":1198,"juz_number":9,"verse_key":"8:38","verse_number":38,"words":[{"chapter_number":0,"code_v1":"ﮣ","id":39705,"line_number":10,"position":1},{"chapter_number":0,"code_v1":"ﮤ","id":39706,"line_number":10,"position":2},{"chapter_number":0,"code_v1":"ﮥ","id":39707,"line_number":11,"position":3},{"chapter_number":0,"code_v1":"ﮦ","id":39708,"line_number":11,"position":4},{"chapter_number":0,"code_v1":"ﮧ","id":39709,"line_number":11,"position":5},{"chapter_number":0,"code_v1":"ﮨ","id":39710,"line_number":11,"position":6},{"chapter_number":0,"code_v1":"ﮩ","id":39711,"line_number":11,"position":7},{"chapter_number":0,"code_v1":"ﮪ","id":39712,"line_number":11,"position":8},{"chapter_number":0,"code_v1":"ﮫ","id":39713,"line_number":11,"position":9},{"chapter_number":0,"code_v1":"ﮬ","id":39714,"line_number":11,"position":10},{"chapter_number":0,"code_v1":"ﮭ","id":39715,"line_number":11,"position":11},{"chapter_number":0,"code_v1":"ﮮ","id":39716,"line_number":11,"position":12},{"chapter_number":0,"code_v1":"ﮯ","id":39717,"line_number":12,"position":13},{"chapter_number":0,"code_v1":"ﮰ","id":39718,"line_number":12,"position":14},{"chapter_number":0,"code_v1":"ﮱ","id":39719,"line_number":12,"position":15},{"chapter_number":0,"code_v1":"ﯓ","id":39720,"line_number":12,"position":16},{"chapter_number":0,"code_v1":"ﯔ","id":39721,"line_number":12,"position":17}]},{"hizb_number":18,"id":1199,"juz_number":9,"verse_key":"8:39","verse_number":39,"words":[{"chapter_number":0,"code_v1":"ﯕ","id":40522,"line_number":12,"position":1},{"chapter_number":0,"code_v1":"ﯖ","id":40523,"line_number":12,"position":2},{"chapter_number":0,"code_v1":"ﯗ","id":40524,"line_number":13,"position":3},{"chapter_number":0,"code_v1":"ﯘ","id":40525,"line_number":13,"position":4},{"chapter_number":0,"code_v1":"ﯙ","id":40526,"line_number":13,"position":5},{"chapter_number":0,"code_v1":"ﯚ","id":40527,"line_number":13,"position":6},{"chapter_number":0,"code_v1":"ﯛ","id":40528,"line_number":13,"position":7},{"chapter_number":0,"code_v1":"ﯜ","id":40529,"line_number":13,"position":8},{"chapter_number":0,"code_v1":"ﯝ","id":40530,"line_number":13,"position":9},{"chapter_number":0,"code_v1":"ﯞ","id":40531,"line_number":13,"position":10},{"chapter_number":0,"code_v1":"ﯟ","id":40532,"line_number":13,"position":11},{"chapter_number":0,"code_v1":"ﯠ","id":40533,"line_number":14,"position":12},{"chapter_number":0,"code_v1":"ﯡ","id":40534,"line_number":14,"position":13},{"chapter_number":0,"code_v1":"ﯢ","id":40535,"line_number":14,"position":14},{"chapter_number":0,"code_v1":"ﯣ","id":40536,"line_number":14,"position":15},{"chapter_number":0,"code_v1":"ﯤ","id":40537,"line_number":14,"position":16},{"chapter_number":0,"code_v1":"ﯥ","id":40538,"line_number":14,"position":17},{"chapter_number":0,"code_v1":"ﯦ","id":40539,"line_number":14,"position":18}]},{"hizb_number":18,"id":1200,"juz_number":9,"verse_key":"8:40","verse_number":40,"words":[{"chapter_number":0,"code_v1":"ﯧ","id":41234,"line_number":14,"position":1},{"chapter_number":0,"code_v1":"ﯨ","id":41235,"line_number":14,"position":2},{"chapter_number":0,"code_v1":"ﯩ","id":41236,"line_number":15,"position":3},{"chapter_number":0,"code_v1":"ﯪ","id":41237,"line_number":15,"position":4},{"chapter_number":0,"code_v1":"ﯫ","id":41238,"line_number":15,"position":5},{"chapter_number":0,"code_v1":"ﯬ","id":41239,"line_number":15,"position":6},{"chapter_number":0,"code_v1":"ﯭ","id":41240,"line_number":15,"position":7},{"chapter_number":0,"code_v1":"ﯮ","id":41241,"line_number":15,"position":8},{"chapter_number":0,"code_v1":"ﯯ","id":41242,"line_number":15,"position":9},{"chapter_number":0,"code_v1":"ﯰ","id":41243,"line_number":15,"position":10},{"chapter_number":0,"code_v1":"ﯱ","id":41244,"line_number":15,"position":11},{"chapter_number":0,"code_v1":"ﯲ","id":41245,"line_number":15,"position":12}]}]